acoustic_toolbox/__init__.py
acoustic_toolbox/_signal.py
acoustic_toolbox/ambisonics.py
acoustic_toolbox/atmosphere.py
acoustic_toolbox/bands.py
acoustic_toolbox/building.py
acoustic_toolbox/cepstrum.py
acoustic_toolbox/criterion.py
acoustic_toolbox/decibel.py
acoustic_toolbox/descriptors.py
acoustic_toolbox/directivity.py
acoustic_toolbox/doppler.py
acoustic_toolbox/generator.py
acoustic_toolbox/imaging.py
acoustic_toolbox/octave.py
acoustic_toolbox/power.py
acoustic_toolbox/quantity.py
acoustic_toolbox/reflection.py
acoustic_toolbox/room.py
acoustic_toolbox/signal.py
acoustic_toolbox/utils.py
acoustic_toolbox/weighting.py
acoustic_toolbox/data/iec_61672_1_2013.csv
acoustic_toolbox/standards/__init__.py
acoustic_toolbox/standards/iec_61260_1_2014.py
acoustic_toolbox/standards/iec_61672_1_2013.py
acoustic_toolbox/standards/iso_1683_2015.py
acoustic_toolbox/standards/iso_1996_1_2003.py
acoustic_toolbox/standards/iso_1996_2_2007.py
acoustic_toolbox/standards/iso_9613_1_1993.py
acoustic_toolbox/standards/iso_tr_25417_2007.py
acoustic_toolbox-0.2.2.dist-info/licenses/LICENSE
acoustic_toolbox-0.2.2.dist-info/WHEEL
acoustic_toolbox-0.2.2.dist-info/METADATA
acoustic_toolbox-0.2.2.dist-info/RECORD
