Metadata-Version: 2.4
Name: acoustic-toolbox
Version: 0.2.2
Summary: Acoustic Toolbox module for Python.
Author: Valentin LE BESCOND, Andrew Mitchell
Requires-Python: >=3.11
Classifier: Programming Language :: Python :: 3
Classifier: Operating System :: OS Independent
License-File: LICENSE
Requires-Dist: numpy>=1.23.5
Requires-Dist: scipy>=1.14.0
Requires-Dist: matplotlib>=3.9.1
Requires-Dist: six>=1.16.0
Requires-Dist: pandas>=2.2.2
Requires-Dist: tabulate>=0.9.0
Requires-Dist: pysoundfile>=0.9.0.post1
Requires-Dist: pyoctaveband>=1.1.3
Requires-Dist: numba>=0.59.0
Requires-Dist: jupyter>=1.0.0 ; extra == "docs"
Requires-Dist: mkdocs>=1.6.1 ; extra == "docs"
Requires-Dist: mkdocs-material>=9.5.9 ; extra == "docs"
Requires-Dist: mkdocs-include-markdown-plugin>=6.0.4 ; extra == "docs"
Requires-Dist: mkdocs-exclude>=1.0.2 ; extra == "docs"
Requires-Dist: mkdocs-macros-plugin>=1.0.4 ; extra == "docs"
Requires-Dist: mkdocstrings[python]>=0.26.2 ; extra == "docs"
Requires-Dist: mkdocs-jupyter>=0.25.1 ; extra == "docs"
Project-URL: Bug Tracker, https://github.com/Universite-Gustave-Eiffel/acoustic-toolbox/issues
Project-URL: Homepage, https://github.com/Universite-Gustave-Eiffel/acoustic-toolbox
Provides-Extra: docs
